reporter/__init__.py
reporter/__main__.py
reporter/main.py
another_one_report_by_csv_cu_homework-0.1.0.dist-info/METADATA
another_one_report_by_csv_cu_homework-0.1.0.dist-info/WHEEL
another_one_report_by_csv_cu_homework-0.1.0.dist-info/top_level.txt
another_one_report_by_csv_cu_homework-0.1.0.dist-info/RECORD
